redistil/__init__.py
redistil/pipeline.py
redistil/redistil.py
redistil-1.1.2.dist-info/LICENSE
redistil-1.1.2.dist-info/METADATA
redistil-1.1.2.dist-info/WHEEL
redistil-1.1.2.dist-info/top_level.txt
redistil-1.1.2.dist-info/RECORD
