Metadata-Version: 2.1
Name: redistil
Version: 1.1.2
Summary: Declarative data types, using Cerberus and Redis
Home-page: https://github.com/adamlwgriffiths/redistil/
Author: Adam Griffiths
Author-email: adam.lw.griffiths@gmail.com
License: BSD 2-Clause License
Platform: UNKNOWN
Classifier: Development Status :: 3 - Alpha
Classifier: Intended Audience :: Developers
Classifier: License :: OSI Approved :: BSD License
Classifier: Programming Language :: Python
Classifier: Topic :: Software Development :: Libraries :: Python Modules
Requires-Python: >=3.5
Requires-Dist: cerberus
Requires-Dist: redis
